{
  "schema": "1.0",
  "comment": "This file maps proto services/RPCs to the corresponding library clients/methods",
  "language": "java",
  "protoPackage": "google.cloud.netapp.v1",
  "libraryPackage": "com.google.cloud.netapp.v1",
  "services": {
    "NetApp": {
      "clients": {
        "grpc": {
          "libraryClient": "NetAppClient",
          "rpcs": {
            "CreateActiveDirectory": {
              "methods": ["createActiveDirectoryAsync", "createActiveDirectoryAsync", "createActiveDirectoryAsync", "createActiveDirectoryOperationCallable", "createActiveDirectoryCallable"]
            },
            "CreateKmsConfig": {
              "methods": ["createKmsConfigAsync", "createKmsConfigAsync", "createKmsConfigAsync", "createKmsConfigOperationCallable", "createKmsConfigCallable"]
            },
            "CreateReplication": {
              "methods": ["createReplicationAsync", "createReplicationAsync", "createReplicationAsync", "createReplicationOperationCallable", "createReplicationCallable"]
            },
            "CreateSnapshot": {
              "methods": ["createSnapshotAsync", "createSnapshotAsync", "createSnapshotAsync", "createSnapshotOperationCallable", "createSnapshotCallable"]
            },
            "CreateStoragePool": {
              "methods": ["createStoragePoolAsync", "createStoragePoolAsync", "createStoragePoolAsync", "createStoragePoolOperationCallable", "createStoragePoolCallable"]
            },
            "CreateVolume": {
              "methods": ["createVolumeAsync", "createVolumeAsync", "createVolumeAsync", "createVolumeOperationCallable", "createVolumeCallable"]
            },
            "DeleteActiveDirectory": {
              "methods": ["deleteActiveDirectoryAsync", "deleteActiveDirectoryAsync", "deleteActiveDirectoryAsync", "deleteActiveDirectoryOperationCallable", "deleteActiveDirectoryCallable"]
            },
            "DeleteKmsConfig": {
              "methods": ["deleteKmsConfigAsync", "deleteKmsConfigAsync", "deleteKmsConfigAsync", "deleteKmsConfigOperationCallable", "deleteKmsConfigCallable"]
            },
            "DeleteReplication": {
              "methods": ["deleteReplicationAsync", "deleteReplicationAsync", "deleteReplicationAsync", "deleteReplicationOperationCallable", "deleteReplicationCallable"]
            },
            "DeleteSnapshot": {
              "methods": ["deleteSnapshotAsync", "deleteSnapshotAsync", "deleteSnapshotAsync", "deleteSnapshotOperationCallable", "deleteSnapshotCallable"]
            },
            "DeleteStoragePool": {
              "methods": ["deleteStoragePoolAsync", "deleteStoragePoolAsync", "deleteStoragePoolAsync", "deleteStoragePoolOperationCallable", "deleteStoragePoolCallable"]
            },
            "DeleteVolume": {
              "methods": ["deleteVolumeAsync", "deleteVolumeAsync", "deleteVolumeAsync", "deleteVolumeOperationCallable", "deleteVolumeCallable"]
            },
            "EncryptVolumes": {
              "methods": ["encryptVolumesAsync", "encryptVolumesOperationCallable", "encryptVolumesCallable"]
            },
            "GetActiveDirectory": {
              "methods": ["getActiveDirectory", "getActiveDirectory", "getActiveDirectory", "getActiveDirectoryCallable"]
            },
            "GetKmsConfig": {
              "methods": ["getKmsConfig", "getKmsConfig", "getKmsConfig", "getKmsConfigCallable"]
            },
            "GetLocation": {
              "methods": ["getLocation", "getLocationCallable"]
            },
            "GetReplication": {
              "methods": ["getReplication", "getReplication", "getReplication", "getReplicationCallable"]
            },
            "GetSnapshot": {
              "methods": ["getSnapshot", "getSnapshot", "getSnapshot", "getSnapshotCallable"]
            },
            "GetStoragePool": {
              "methods": ["getStoragePool", "getStoragePool", "getStoragePool", "getStoragePoolCallable"]
            },
            "GetVolume": {
              "methods": ["getVolume", "getVolume", "getVolume", "getVolumeCallable"]
            },
            "ListActiveDirectories": {
              "methods": ["listActiveDirectories", "listActiveDirectories", "listActiveDirectories", "listActiveDirectoriesPagedCallable", "listActiveDirectoriesCallable"]
            },
            "ListKmsConfigs": {
              "methods": ["listKmsConfigs", "listKmsConfigs", "listKmsConfigs", "listKmsConfigsPagedCallable", "listKmsConfigsCallable"]
            },
            "ListLocations": {
              "methods": ["listLocations", "listLocationsPagedCallable", "listLocationsCallable"]
            },
            "ListReplications": {
              "methods": ["listReplications", "listReplications", "listReplications", "listReplicationsPagedCallable", "listReplicationsCallable"]
            },
            "ListSnapshots": {
              "methods": ["listSnapshots", "listSnapshots", "listSnapshots", "listSnapshotsPagedCallable", "listSnapshotsCallable"]
            },
            "ListStoragePools": {
              "methods": ["listStoragePools", "listStoragePools", "listStoragePools", "listStoragePoolsPagedCallable", "listStoragePoolsCallable"]
            },
            "ListVolumes": {
              "methods": ["listVolumes", "listVolumes", "listVolumes", "listVolumesPagedCallable", "listVolumesCallable"]
            },
            "ResumeReplication": {
              "methods": ["resumeReplicationAsync", "resumeReplicationOperationCallable", "resumeReplicationCallable"]
            },
            "ReverseReplicationDirection": {
              "methods": ["reverseReplicationDirectionAsync", "reverseReplicationDirectionOperationCallable", "reverseReplicationDirectionCallable"]
            },
            "RevertVolume": {
              "methods": ["revertVolumeAsync", "revertVolumeOperationCallable", "revertVolumeCallable"]
            },
            "StopReplication": {
              "methods": ["stopReplicationAsync", "stopReplicationOperationCallable", "stopReplicationCallable"]
            },
            "UpdateActiveDirectory": {
              "methods": ["updateActiveDirectoryAsync", "updateActiveDirectoryAsync", "updateActiveDirectoryOperationCallable", "updateActiveDirectoryCallable"]
            },
            "UpdateKmsConfig": {
              "methods": ["updateKmsConfigAsync", "updateKmsConfigAsync", "updateKmsConfigOperationCallable", "updateKmsConfigCallable"]
            },
            "UpdateReplication": {
              "methods": ["updateReplicationAsync", "updateReplicationAsync", "updateReplicationOperationCallable", "updateReplicationCallable"]
            },
            "UpdateSnapshot": {
              "methods": ["updateSnapshotAsync", "updateSnapshotAsync", "updateSnapshotOperationCallable", "updateSnapshotCallable"]
            },
            "UpdateStoragePool": {
              "methods": ["updateStoragePoolAsync", "updateStoragePoolAsync", "updateStoragePoolOperationCallable", "updateStoragePoolCallable"]
            },
            "UpdateVolume": {
              "methods": ["updateVolumeAsync", "updateVolumeAsync", "updateVolumeOperationCallable", "updateVolumeCallable"]
            },
            "VerifyKmsConfig": {
              "methods": ["verifyKmsConfig", "verifyKmsConfigCallable"]
            }
          }
        }
      }
    }
  }
}