<?xml version="1.0" encoding="UTF-8"?>
<!-- see http://www.mojohaus.org/clirr-maven-plugin/examples/ignored-differences.html -->
<differences>
  <!-- TODO: remove once 1.x.y-alpha version is stabilized -->
  <difference>
    <differenceType>8001</differenceType>
    <className>com/google/cloud/compute/**</className>
  </difference>
  <!-- TODO: remove once 1.x.y-alpha version is stabilized -->
  <!-- Originally caused by https://github.com/googleapis/googleapis-discovery/pull/31 -->
  <difference>
    <differenceType>6003</differenceType>
    <className>com/google/cloud/compute/**</className>
    <field>*FIELD_NUMBER</field>
  </difference>
  <!-- TODO: remove once 1.x.y-alpha version is stabilized -->
  <!-- Originally caused by https://github.com/googleapis/googleapis-discovery/pull/31 -->
  <difference>
    <differenceType>6003</differenceType>
    <className>com/google/cloud/compute/**</className>
    <field>*_VALUE</field>
  </difference>
  <!-- TODO: remove once 1.x.y-alpha version is stabilized -->
  <!-- Originally caused by https://github.com/googleapis/googleapis-discovery/pull/30-->
  <difference>
    <differenceType>7012</differenceType>
    <className>com/google/cloud/compute/**</className>
    <method>boolean has*(*)</method>
  </difference>
  <!-- TODO: remove once 1.x.y-alpha version is stabilized -->
  <!-- Originally caused by https://github.com/googleapis/java-compute/pull/476-->
  <difference>
    <differenceType>7002</differenceType>
    <className>com/google/cloud/compute/**</className>
    <method>int getDefaultServicePort()</method>
  </difference>
  <!-- TODO: remove once 1.x.y-alpha version is stabilized -->
  <!-- Originally caused by https://github.com/googleapis/java-compute/pull/476-->
  <difference>
    <differenceType>6010</differenceType>
    <className>com/google/cloud/compute/**</className>
    <field>*MethodDescriptor</field>
  </difference>
  <!-- Removes method -->
  <difference>
    <differenceType>7002</differenceType>
    <className>com/google/cloud/compute/v1/**</className>
    <method>* delete*(*)</method>
  </difference>
  <difference>
    <differenceType>7002</differenceType>
    <className>com/google/cloud/compute/v1/**</className>
    <method>* insert*(*)</method>
  </difference>
  <difference>
    <differenceType>7002</differenceType>
    <className>com/google/cloud/compute/v1/**</className>
    <method>* patch*(*)</method>
  </difference>
  <difference>
    <differenceType>7002</differenceType>
    <className>com/google/cloud/compute/v1/**</className>
    <method>* update*(*)</method>
  </difference>
  <difference>
    <differenceType>7002</differenceType>
    <className>com/google/cloud/compute/v1/**</className>
    <method>* set*(*)</method>
  </difference>
  <difference>
    <differenceType>7002</differenceType>
    <className>com/google/cloud/compute/v1/**</className>
    <method>* remove*(*)</method>
  </difference>
  <difference>
    <differenceType>7002</differenceType>
    <className>com/google/cloud/compute/v1/**</className>
    <method>* add*(*)</method>
  </difference>
  <difference>
    <differenceType>7002</differenceType>
    <className>com/google/cloud/compute/v1/**</className>
    <method>* expand*(*)</method>
  </difference>
  <difference>
    <differenceType>7002</differenceType>
    <className>com/google/cloud/compute/v1/**</className>
    <method>* invalidate*(*)</method>
  </difference>
  <difference>
    <differenceType>7002</differenceType>
    <className>com/google/cloud/compute/v1/**</className>
    <method>* resize(*)</method>
  </difference>
  <difference>
    <differenceType>7002</differenceType>
    <className>com/google/cloud/compute/v1/**</className>
    <method>* bulk*(*)</method>
  </difference>
  <difference>
    <differenceType>7002</differenceType>
    <className>com/google/cloud/compute/v1/**</className>
    <method>* create*(*)</method>
  </difference>
  <difference>
    <differenceType>7002</differenceType>
    <className>com/google/cloud/compute/v1/**</className>
    <method>* apply*(*)</method>
  </difference>
  <difference>
    <differenceType>7002</differenceType>
    <className>com/google/cloud/compute/v1/**</className>
    <method>* abandon*(*)</method>
  </difference>
  <difference>
    <differenceType>7002</differenceType>
    <className>com/google/cloud/compute/v1/**</className>
    <method>* recreate*(*)</method>
  </difference>
  <difference>
    <differenceType>7002</differenceType>
    <className>com/google/cloud/compute/v1/**</className>
    <method>* enable*(*)</method>
  </difference>
  <difference>
    <differenceType>7002</differenceType>
    <className>com/google/cloud/compute/v1/**</className>
    <method>* disable*(*)</method>
  </difference>
  <difference>
    <differenceType>7002</differenceType>
    <className>com/google/cloud/compute/v1/**</className>
    <method>* move*(*)</method>
  </difference>
  <difference>
    <differenceType>7002</differenceType>
    <className>com/google/cloud/compute/v1/**</className>
    <method>* switch*(*)</method>
  </difference>
  <difference>
    <differenceType>7002</differenceType>
    <className>com/google/cloud/compute/v1/**</className>
    <method>* attach*(*)</method>
  </difference>
  <difference>
    <differenceType>7002</differenceType>
    <className>com/google/cloud/compute/v1/**</className>
    <method>* start*(*)</method>
  </difference>
  <difference>
    <differenceType>7002</differenceType>
    <className>com/google/cloud/compute/v1/**</className>
    <method>* simulate*(*)</method>
  </difference>
  <difference>
    <differenceType>7002</differenceType>
    <className>com/google/cloud/compute/v1/**</className>
    <method>* detach*(*)</method>
  </difference>
  <difference>
    <differenceType>7002</differenceType>
    <className>com/google/cloud/compute/v1/**</className>
    <method>* clone*(*)</method>
  </difference>
  <difference>
    <differenceType>7002</differenceType>
    <className>com/google/cloud/compute/v1/**</className>
    <method>* deprecate*(*)</method>
  </difference>
  <difference>
    <differenceType>7002</differenceType>
    <className>com/google/cloud/compute/v1/**</className>
    <method>* reset*(*)</method>
  </difference>
  <difference>
    <differenceType>7002</differenceType>
    <className>com/google/cloud/compute/v1/**</className>
    <method>* stop*(*)</method>
  </difference>
</differences>
