{
    "api_shortname": "billingbudgets",
    "name_pretty": "Cloud Billing Budgets",
    "product_documentation": "https://cloud.google.com/billing/docs/how-to/budgets",
    "client_documentation": "https://cloud.google.com/java/docs/reference/google-cloud-billingbudgets/latest/overview",
    "api_description": "allows you to avoid surprises on your bill by creating budgets to monitor all your Google Cloud charges in one place.",
    "release_level": "stable",
    "language": "java",
    "transport": "grpc",
    "repo": "googleapis/java-billingbudgets",
    "repo_short": "java-billingbudgets",
    "distribution_name": "com.google.cloud:google-cloud-billingbudgets",
    "api_id": "billingbudgets.googleapis.com",
    "requires_billing": true,
    "library_type": "GAPIC_AUTO"
}
